allure_handle/__init__.py
allure_handle/allure_handle.py
allure_handle/example.py
allurehandle_lit-1.0.1.dist-info/METADATA
allurehandle_lit-1.0.1.dist-info/WHEEL
allurehandle_lit-1.0.1.dist-info/top_level.txt
allurehandle_lit-1.0.1.dist-info/RECORD
