Metadata-Version: 2.1
Name: allurehandle-lit
Version: 1.0.1
Summary: 轻量级 Allure 报告处理工具，用于 pytest 测试框架
Home-page: https://github.com/Aquarius-0455/Allurehandle-Lit
Author: Lit
Author-email: 
License: MIT
Keywords: allure,pytest,testing,report
Classifier: Development Status :: 4 - Beta
Classifier: Intended Audience :: Developers
Classifier: Topic :: Software Development :: Testing
Classifier: License :: OSI Approved :: MIT License
Classifier: Programming Language :: Python :: 3
Classifier: Programming Language :: Python :: 3.7
Classifier: Programming Language :: Python :: 3.8
Classifier: Programming Language :: Python :: 3.9
Classifier: Programming Language :: Python :: 3.10
Classifier: Programming Language :: Python :: 3.11
Requires-Python: >=3.7
Requires-Dist: allure-pytest>=2.13.0
